Metadata-Version: 2.1
Name: simple-linear-algebra
Version: 0.0.1
Summary: A small package to implement basic linear algebra operations
Home-page: https://github.com/caroger/linear_algebra
Author: Roger Hu
Author-email: handeasy@gmail.com
License: UNKNOWN
Platform: UNKNOWN
Classifier: Programming Language :: Python :: 3
Classifier: License :: OSI Approved :: MIT License
Classifier: Operating System :: OS Independent
Requires-Python: >=3.6
